<?xml version="1.0" encoding="UTF-8" standalone="yes"?>
<?xml-stylesheet type="text/xsl" href="_assets/recipe.xsl"?>

<recipe lang="en-uk">   <title><![CDATA[Eel and broccoli pie]]></title>
   <description><![CDATA[]]></description>
   <source><![CDATA[]]></source>
   <cuisine>
      <style></style>
      <region></region>
      <approach></approach>
   </cuisine>
   <tags>
      <tag></tag>
   </tags>
   <directions>
      <step><![CDATA[dissolve in 320 ml water, warm, 5m]]></step>
      <step><![CDATA[add flour bit by bit and knead, 10m]]></step>
      <step><![CDATA[rest in greased bowl, covered in kitchen towel until doubled in size, 2h]]></step>
      <step><![CDATA[sauté in 2 tbs oil, olive on med, 10m]]></step>
      <step><![CDATA[add]]></step>
      <step><![CDATA[add on low, 10m]]></step>
      <step><![CDATA[put anchovy fillets in a skillet]]></step>
      <step><![CDATA[add]]></step>
      <step><![CDATA[add]]></step>
      <step><![CDATA[add]]></step>
      <step><![CDATA[lay broccoli on top]]></step>
      <step><![CDATA[drizzle oil on top]]></step>
      <step><![CDATA[add olives on top]]></step>
      <step><![CDATA[add]]></step>
      <step><![CDATA[drizzle wine on top]]></step>
      <step><![CDATA[cover and simmer without stirring on low, 12m]]></step>
      <step><![CDATA[Drain and mix with the tomatoes]]></step>
      <step><![CDATA[Roll out the dough in a disk, ladle out the drained fillings, fold like a calzone, and puncture. ]]></step>
      <step><![CDATA[Bake until ready on 190°, 35m]]></step>
   </directions>
   <ingredients>
      <serves></serves>
      <group>
         <ingredient>
            <quantity>3</quantity>
            <measurement>tsp</measurement>
            <name>fresh yeast</name>
            <preparation>or dry</preparation>
         </ingredient>
         <ingredient>
            <quantity>480</quantity>
            <measurement>g</measurement>
            <name>flour</name>
            <preparation></preparation>
         </ingredient>
         <ingredient>
            <quantity>1</quantity>
            <measurement></measurement>
            <name>onion</name>
            <preparation>sliced</preparation>
         </ingredient>
         <ingredient>
            <quantity>300</quantity>
            <measurement>g</measurement>
            <name>eel</name>
            <preparation>cleaned, minced</preparation>
         </ingredient>
         <ingredient>
            <quantity>2</quantity>
            <measurement></measurement>
            <name>tomatoes</name>
            <preparation>peeled, deseeded, chopped</preparation>
         </ingredient>
         <ingredient>
            <quantity>2</quantity>
            <measurement></measurement>
            <name>anchovy fillets</name>
            <preparation></preparation>
         </ingredient>
         <ingredient>
            <quantity>0.5</quantity>
            <measurement></measurement>
            <name>onion</name>
            <preparation>sliced</preparation>
         </ingredient>
         <ingredient>
            <quantity>1</quantity>
            <measurement>tbsp</measurement>
            <name>caciocavallo cheese</name>
            <preparation>grated</preparation>
         </ingredient>
         <ingredient>
            <quantity>1</quantity>
            <measurement>tbsp</measurement>
            <name>black olives</name>
            <preparation>pitted and chopped</preparation>
         </ingredient>
         <ingredient>
            <quantity>400</quantity>
            <measurement>g</measurement>
            <name>broccoli</name>
            <preparation>split into florets</preparation>
         </ingredient>
         <ingredient>
            <quantity>2</quantity>
            <measurement>tbsp</measurement>
            <name>olive oil</name>
            <preparation></preparation>
         </ingredient>
         <ingredient>
            <quantity>1</quantity>
            <measurement>tbsp</measurement>
            <name>black olives</name>
            <preparation>pitted and chopped</preparation>
         </ingredient>
         <ingredient>
            <quantity></quantity>
            <measurement></measurement>
            <name>salt</name>
            <preparation></preparation>
         </ingredient>
         <ingredient>
            <quantity>60</quantity>
            <measurement>ml</measurement>
            <name>red wine</name>
            <preparation></preparation>
         </ingredient>
      </group>
   </ingredients>
</recipe>
